chatmachine/__init__.py
chatmachine/core.py
chatmachine/py.typed
chatmachine-0.1.5.dist-info/METADATA
chatmachine-0.1.5.dist-info/WHEEL
chatmachine-0.1.5.dist-info/licenses/LICENSE
chatmachine-0.1.5.dist-info/RECORD
