Metadata-Version: 2.4
Name: chatmachine
Version: 0.1.5
Summary: Add your description here
Author-email: tomaszbk <zubik.tomas@gmail.com>
License-File: LICENSE
Requires-Python: >=3.9
Requires-Dist: pydantic>=2.11.3
